glyphs/__init__.py
glyphs/backports/__init__.py
glyphs/backports/lru_cache.py
glyphs/helpers/ImmutableObject.py
glyphs/helpers/ImmutableType.py
glyphs/helpers/__init__.py
glyphs/ro/ROGlyph.py
glyphs/ro/__init__.py
glyphs/rw/RWGlyph.py
glyphs/rw/ResettableGlyph.py
glyphs/rw/__init__.py
glyphs/utils/BooleanUtils.py
glyphs/utils/DictUtils.py
glyphs/utils/StringUtils.py
glyphs/utils/__init__.py
glyphs-0.1.3.dist-info/LICENSE
glyphs-0.1.3.dist-info/METADATA
glyphs-0.1.3.dist-info/WHEEL
glyphs-0.1.3.dist-info/top_level.txt
glyphs-0.1.3.dist-info/RECORD
